celery_eternal/__init__.py
celery_eternal/test/__init__.py
celery_eternal/test/test_eternal.py
celery_eternal-0.1.1.dist-info/LICENSE.md
celery_eternal-0.1.1.dist-info/METADATA
celery_eternal-0.1.1.dist-info/WHEEL
celery_eternal-0.1.1.dist-info/top_level.txt
celery_eternal-0.1.1.dist-info/RECORD
