Metadata-Version: 2.1
Name: celery-eternal
Version: 0.1.1
Summary: Celery task subclass for jobs that should run forever
Home-page: http://celery-eternal.readthedocs.io/
Author: Leo Singer
Author-email: leo.singer@ligo.org
License: GPL-2+
Platform: UNKNOWN
Classifier: Development Status :: 3 - Alpha
Classifier: License :: OSI Approved :: GNU General Public License v2 or later (GPLv2+)
Classifier: Operating System :: POSIX
Classifier: Programming Language :: Python
Classifier: Programming Language :: Python :: 2
Classifier: Programming Language :: Python :: 2.7
Classifier: Programming Language :: Python :: 3
Classifier: Programming Language :: Python :: 3.4
Classifier: Programming Language :: Python :: 3.5
Classifier: Programming Language :: Python :: 3.6
Classifier: Topic :: Software Development :: Object Brokering
Classifier: Topic :: System :: Distributed Computing
Requires-Dist: celery[redis] (>=4.1.0)
Requires-Dist: celery-singleton (>=0.1.1)
